pdf_anonymizer_core/__init__.py
pdf_anonymizer_core/call_llm.py
pdf_anonymizer_core/conf.py
pdf_anonymizer_core/core.py
pdf_anonymizer_core/llm_provider.py
pdf_anonymizer_core/load_and_extract.py
pdf_anonymizer_core/utils.py
pdf_anonymizer_core/prompts/__init__.py
pdf_anonymizer_core/prompts/detailed.py
pdf_anonymizer_core/prompts/simple.py
pdf_anonymizer_core-0.3.2.dist-info/METADATA
pdf_anonymizer_core-0.3.2.dist-info/WHEEL
pdf_anonymizer_core-0.3.2.dist-info/top_level.txt
pdf_anonymizer_core-0.3.2.dist-info/RECORD
