Metadata-Version: 2.4
Name: pdf-anonymizer-core
Version: 0.3.2
Summary: A core library to anonymize PDF, Markdown, and plain text files using LLMs.
Author-email: Leonid Ganeline <leo.gan.57@gmail.com>
License: MIT
Project-URL: repository, https://github.com/leo-gan/anonymizer
Requires-Python: >=3.10
Requires-Dist: python-dotenv
Requires-Dist: pymupdf4llm
Requires-Dist: langchain-text-splitters
Provides-Extra: google
Requires-Dist: google-genai; extra == "google"
Provides-Extra: ollama
Requires-Dist: ollama; extra == "ollama"
Provides-Extra: huggingface
Requires-Dist: huggingface-hub; extra == "huggingface"
Provides-Extra: openrouter
Requires-Dist: openai; extra == "openrouter"
Provides-Extra: openai
Requires-Dist: openai; extra == "openai"
Provides-Extra: anthropic
Requires-Dist: anthropic; extra == "anthropic"
